soil_power_sensor_protobuf/__init__.py
soil_power_sensor_protobuf/cli.py
soil_power_sensor_protobuf/soil_power_sensor_pb2.py
soil_power_sensor_protobuf/calibrate/PingSMU.py
soil_power_sensor_protobuf/calibrate/PingSPS.py
soil_power_sensor_protobuf/calibrate/README.md
soil_power_sensor_protobuf/calibrate/__init__.py
soil_power_sensor_protobuf/calibrate/linear_regression.py
soil_power_sensor_protobuf/calibrate/plots.py
soil_power_sensor_protobuf/calibrate/recorder.py
soil_power_sensor_protobuf/calibrate/requirements.txt
soil_power_sensor_protobuf/config/README.md
soil_power_sensor_protobuf/config/__init__.py
soil_power_sensor_protobuf/config/adv_trace.py
soil_power_sensor_protobuf/config/user_config.py
soil_power_sensor_protobuf/proto/__init__.py
soil_power_sensor_protobuf/proto/decode.py
soil_power_sensor_protobuf/proto/encode.py
soil_power_sensor_protobuf/proto/esp32.py
soil_power_sensor_protobuf/proto/soil_power_sensor_pb2.py
soil_power_sensor_protobuf-2.3.1.dist-info/METADATA
soil_power_sensor_protobuf-2.3.1.dist-info/WHEEL
soil_power_sensor_protobuf-2.3.1.dist-info/entry_points.txt
soil_power_sensor_protobuf-2.3.1.dist-info/licenses/LICENSE
soil_power_sensor_protobuf-2.3.1.dist-info/RECORD
