Metadata-Version: 2.4
Name: soil-power-sensor-protobuf
Version: 2.3.1
Summary: Python package for encoding/decoding measurement data from the Soil Power Sensor
Project-URL: Homepage, https://github.com/jlab-sensing/soil-power-sensor-firmware
Project-URL: Issues, https://github.com/jlab-sensing/soil-power-sensor-firmware/issues
Author-email: John Madden <jmadden173@pm.me>
License-File: LICENSE
Classifier: License :: OSI Approved :: MIT License
Classifier: Operating System :: OS Independent
Classifier: Programming Language :: Python :: 3
Requires-Python: >=3.11
Requires-Dist: matplotlib
Requires-Dist: pandas
Requires-Dist: protobuf>5.0.0
Requires-Dist: pyqt5
Requires-Dist: pyserial
Requires-Dist: scikit-learn
Requires-Dist: tqdm
